handle_exception/__init__.py
handle_exception/handle_exception.py
tests/__init__.py
tests/test_handle_exception.py
handle_exception-1.0.1.dist-info/METADATA
handle_exception-1.0.1.dist-info/WHEEL
handle_exception-1.0.1.dist-info/top_level.txt
handle_exception-1.0.1.dist-info/RECORD
