Metadata-Version: 2.1
Name: handle-exception
Version: 1.0.1
Summary: A Python library for handling exceptions in a clean and organized way
Home-page: https://github.com/dillibk777/handle_exception
Author: Dilli Babu Kadati
Author-email: dillibabukadati777@gmail.com
License: UNKNOWN
Platform: UNKNOWN
Classifier: Development Status :: 3 - Alpha
Classifier: Intended Audience :: Developers
Classifier: Programming Language :: Python :: 3
Classifier: Programming Language :: Python :: 3.7
Classifier: Programming Language :: Python :: 3.8
Classifier: Programming Language :: Python :: 3.9
Classifier: License :: OSI Approved :: MIT License
Classifier: Operating System :: OS Independent
